__init__.py
agents/__init__.py
cli/__init__.py
cli/confiture_extensions.py
cli/diff.py
cli/docs.py
cli/generate.py
cli/orchestrator.py
cli/validate.py
core/__init__.py
core/ast_models.py
core/exceptions.py
core/reserved_fields.py
core/scalar_types.py
core/separators.py
core/specql_parser.py
core/type_registry.py
generators/__init__.py
generators/app_schema_generator.py
generators/app_wrapper_generator.py
generators/comment_generator.py
generators/composite_type_generator.py
generators/constraint_generator.py
generators/core_logic_generator.py
generators/function_generator.py
generators/index_generator.py
generators/schema_orchestrator.py
generators/sql_utils.py
generators/table_generator.py
generators/trinity_helper_generator.py
generators/actions/__init__.py
generators/actions/action_compiler.py
generators/actions/action_context.py
generators/actions/action_orchestrator.py
generators/actions/action_validator.py
generators/actions/composite_type_builder.py
generators/actions/conditional_compiler.py
generators/actions/database_operation_compiler.py
generators/actions/error_codes.py
generators/actions/expression_compiler.py
generators/actions/function_generator.py
generators/actions/function_scaffolding.py
generators/actions/identifier_recalc_generator.py
generators/actions/impact_metadata_compiler.py
generators/actions/success_response_generator.py
generators/actions/trinity_resolver.py
generators/actions/validation_step_compiler.py
generators/actions/step_compilers/__init__.py
generators/actions/step_compilers/call_compiler.py
generators/actions/step_compilers/delete_compiler.py
generators/actions/step_compilers/fk_resolver.py
generators/actions/step_compilers/foreach_compiler.py
generators/actions/step_compilers/if_compiler.py
generators/actions/step_compilers/insert_compiler.py
generators/actions/step_compilers/notify_compiler.py
generators/actions/step_compilers/refresh_table_view_compiler.py
generators/actions/step_compilers/rich_type_handler.py
specql_generator-0.5.0.dist-info/licenses/LICENSE
specql_generator-0.5.0.dist-info/METADATA
specql_generator-0.5.0.dist-info/WHEEL
specql_generator-0.5.0.dist-info/entry_points.txt
specql_generator-0.5.0.dist-info/top_level.txt
specql_generator-0.5.0.dist-info/RECORD
