Metadata-Version: 2.4
Name: specql-generator
Version: 0.5.0
Summary: SpecQL schema generator - Business-focused YAML to PostgreSQL + GraphQL
Author-email: Lionel Hamayon <lionel.hamayon@evolution-digitale.fr>
License: MIT
Requires-Python: >=3.11
License-File: LICENSE
Requires-Dist: pyyaml>=6.0
Requires-Dist: jinja2>=3.1.2
Requires-Dist: click>=8.1.0
Requires-Dist: rich>=13.0.0
Requires-Dist: psycopg2-binary>=2.9.0
Requires-Dist: psycopg>=3.2.12
Requires-Dist: fraiseql-confiture>=0.3.0
Requires-Dist: faker>=37.12.0
Provides-Extra: dev
Requires-Dist: pytest>=7.4.0; extra == "dev"
Requires-Dist: pytest-cov>=4.1.0; extra == "dev"
Requires-Dist: pytest-asyncio>=0.21.0; extra == "dev"
Requires-Dist: ruff>=0.1.0; extra == "dev"
Requires-Dist: mypy>=1.5.0; extra == "dev"
Requires-Dist: black>=23.0.0; extra == "dev"
Requires-Dist: types-pyyaml>=6.0.0; extra == "dev"
Dynamic: license-file
